.bandit
.git_archival.txt
.gitattributes
.gitignore
.pre-commit-config.yaml
.readthedocs.yml
BMNG_clouds_201109181715_areaT2.png
CHANGELOG.md
LICENSE.txt
MANIFEST.in
README.rst
RELEASING.md
pyproject.toml
setup.cfg
setup.py
.github/dependabot.yml
.github/workflows/ci.yaml
.github/workflows/deploy-sdist.yaml
continuous_integration/environment.yaml
doc/Makefile
doc/source/conf.py
doc/source/index.rst
doc/source/installation.rst
doc/source/usage.rst
doc/source/_static/.gitkeep
doc/source/api/.gitkeep
doc/source/images/alignment_image1.png
doc/source/images/alignment_image2.png
doc/source/images/alignment_image3.png
doc/source/images/alignment_image4.png
doc/source/images/logo_and_scale1.png
doc/source/images/logo_and_scale2.png
doc/source/images/logo_and_scale3.png
doc/source/images/logo_image.png
doc/source/images/style_retention.png
doc/source/images/text_and_logo_image.png
logos/NASA_Logo.gif
logos/NASA_Logo.jpg
logos/VI_Logo_Transp.png
logos/esa_small.jpg
logos/eumetsat.png
logos/eumetsat2.png
logos/noaa_logo.jpg
logos/pytroll_light_big.png
logos/snaps_logo.png
logos/vi-logo-350x350.gif
logos/vi-logo-350x350.png
logos/vilogo_x50.gif
pydecorate/__init__.py
pydecorate/decorator.py
pydecorate/decorator_agg.py
pydecorate/decorator_base.py
pydecorate/version.py
pydecorate.egg-info/PKG-INFO
pydecorate.egg-info/SOURCES.txt
pydecorate.egg-info/dependency_links.txt
pydecorate.egg-info/not-zip-safe
pydecorate.egg-info/requires.txt
pydecorate.egg-info/top_level.txt
pydecorate/fonts/DejaVuSerif.ttf
pydecorate/fonts/__init__.py
pydecorate/tests/__init__.py
pydecorate/tests/test_decorator_agg.py
pydecorate/tests/test_legacy.py