Metadata-Version: 2.1
Name: pydecorate
Version: 0.4.0
Summary: Decorating PIL images: logos, texts, pallettes
Home-page: https://github.com/pytroll/pydecorate
Author: Hrobjartur Thorsteinsson
Author-email: thorsteinssonh@gmail.com
License: GPLv3+
Classifier: Development Status :: 4 - Beta
Classifier: Intended Audience :: Science/Research
Classifier: License :: OSI Approved :: GNU General Public License v3 or later (GPLv3+)
Classifier: Operating System :: OS Independent
Classifier: Programming Language :: Python
Classifier: Topic :: Scientific/Engineering
Requires-Python: >=3.9
License-File: LICENSE.txt
Requires-Dist: pillow
Requires-Dist: aggdraw
Requires-Dist: numpy
Provides-Extra: tests
Requires-Dist: pytest; extra == "tests"
Requires-Dist: pytest-cov; extra == "tests"
Requires-Dist: trollimage; extra == "tests"
Provides-Extra: docs
Requires-Dist: sphinx; extra == "docs"
Requires-Dist: sphinx_rtd_theme; extra == "docs"
Requires-Dist: sphinxcontrib-apidoc; extra == "docs"
Requires-Dist: trollimage; extra == "docs"
Requires-Dist: pytest; extra == "docs"
